dmglib.py
dmglib-0.9.6.dist-info/LICENSE
dmglib-0.9.6.dist-info/METADATA
dmglib-0.9.6.dist-info/WHEEL
dmglib-0.9.6.dist-info/top_level.txt
dmglib-0.9.6.dist-info/RECORD
