Metadata-Version: 2.1
Name: dmglib
Version: 0.9.6
Summary: Work with macOS DMG disk images
Home-page: https://github.com/0xbf00/dmglib
Author: Jakob Rieck
Author-email: jakobrieck+pypi@gmail.com
License: MIT License
Classifier: Programming Language :: Python :: 3.6
Classifier: Operating System :: MacOS
Classifier: Development Status :: 5 - Production/Stable
Classifier: Intended Audience :: Developers
Classifier: License :: OSI Approved :: MIT License
Provides: dmglib
License-File: LICENSE
